opendp/__init__.py
opendp/whitenoise/__init__.py
opendp/whitenoise/report.py
opendp/whitenoise/ast/__init__.py
opendp/whitenoise/ast/ast.py
opendp/whitenoise/ast/expression.py
opendp/whitenoise/ast/tokens.py
opendp/whitenoise/ast/validate.py
opendp/whitenoise/ast/expressions/__init__.py
opendp/whitenoise/ast/expressions/date.py
opendp/whitenoise/ast/expressions/logical.py
opendp/whitenoise/ast/expressions/numeric.py
opendp/whitenoise/ast/expressions/sql.py
opendp/whitenoise/ast/expressions/string.py
opendp/whitenoise/client/__init__.py
opendp/whitenoise/client/restclient/__init__.py
opendp/whitenoise/client/restclient/rest_client.py
opendp/whitenoise/client/restclient/version.py
opendp/whitenoise/client/restclient/models/__init__.py
opendp/whitenoise/client/restclient/models/dataset_document.py
opendp/whitenoise/client/restclient/models/dataset_read_release_request.py
opendp/whitenoise/client/restclient/models/dataset_read_request.py
opendp/whitenoise/client/restclient/models/dataverse_details.py
opendp/whitenoise/client/restclient/models/executerun_ok_response.py
opendp/whitenoise/client/restclient/models/local_csv_details.py
opendp/whitenoise/client/restclient/models/project_run_details.py
opendp/whitenoise/client/restclient/models/register_ok_response.py
opendp/whitenoise/client/restclient/models/release_dataset_document.py
opendp/whitenoise/client/restclient/models/secret.py
opendp/whitenoise/client/restclient/models/secret_put_success.py
opendp/whitenoise/data/__init__.py
opendp/whitenoise/data/adapters.py
opendp/whitenoise/data/dataset_adapter.py
opendp/whitenoise/data/dataverse_adapter.py
opendp/whitenoise/data/local_csv_adapter.py
opendp/whitenoise/evaluation/__init__.py
opendp/whitenoise/evaluation/_aggregation.py
opendp/whitenoise/evaluation/_dp_verification.py
opendp/whitenoise/evaluation/_exploration.py
opendp/whitenoise/evaluation/aggregation.py
opendp/whitenoise/evaluation/dp_verification.py
opendp/whitenoise/evaluation/exploration.py
opendp_whitenoise-0.1.2.dist-info/METADATA
opendp_whitenoise-0.1.2.dist-info/WHEEL
opendp_whitenoise-0.1.2.dist-info/top_level.txt
opendp_whitenoise-0.1.2.dist-info/RECORD
